NiuKeyunYinggangMianshiZhentiBaodian20212022Fix1/README.md
NiuKeyunYinggangMianshiZhentiBaodian20212022Fix1/__init__.py
NiuKeyunYinggangMianshiZhentiBaodian20212022Fix1/__main__.py
NiuKeyunYinggangMianshiZhentiBaodian20212022Fix1/file.epub
NiuKeyunYinggangMianshiZhentiBaodian20212022Fix1/index.html
NiuKeyunYinggangMianshiZhentiBaodian20212022Fix1/css/__init__.py
NiuKeyunYinggangMianshiZhentiBaodian20212022Fix1/css/annotations.css
NiuKeyunYinggangMianshiZhentiBaodian20212022Fix1/css/main.css
NiuKeyunYinggangMianshiZhentiBaodian20212022Fix1/css/normalize.css
NiuKeyunYinggangMianshiZhentiBaodian20212022Fix1/css/popup.css
NiuKeyunYinggangMianshiZhentiBaodian20212022Fix1/font/__init__.py
NiuKeyunYinggangMianshiZhentiBaodian20212022Fix1/font/fontello.eot
NiuKeyunYinggangMianshiZhentiBaodian20212022Fix1/font/fontello.svg
NiuKeyunYinggangMianshiZhentiBaodian20212022Fix1/font/fontello.ttf
NiuKeyunYinggangMianshiZhentiBaodian20212022Fix1/font/fontello.woff
NiuKeyunYinggangMianshiZhentiBaodian20212022Fix1/img/__init__.py
NiuKeyunYinggangMianshiZhentiBaodian20212022Fix1/img/annotator-glyph-sprite.png
NiuKeyunYinggangMianshiZhentiBaodian20212022Fix1/img/annotator-icon-sprite.png
NiuKeyunYinggangMianshiZhentiBaodian20212022Fix1/img/apple-touch-icon.png
NiuKeyunYinggangMianshiZhentiBaodian20212022Fix1/img/cancelfullscreen.png
NiuKeyunYinggangMianshiZhentiBaodian20212022Fix1/img/close.png
NiuKeyunYinggangMianshiZhentiBaodian20212022Fix1/img/fullscreen.png
NiuKeyunYinggangMianshiZhentiBaodian20212022Fix1/img/loader.gif
NiuKeyunYinggangMianshiZhentiBaodian20212022Fix1/img/menu-icon.png
NiuKeyunYinggangMianshiZhentiBaodian20212022Fix1/img/save.png
NiuKeyunYinggangMianshiZhentiBaodian20212022Fix1/img/saved.png
NiuKeyunYinggangMianshiZhentiBaodian20212022Fix1/img/settings-s.png
NiuKeyunYinggangMianshiZhentiBaodian20212022Fix1/img/settings.png
NiuKeyunYinggangMianshiZhentiBaodian20212022Fix1/img/star.png
NiuKeyunYinggangMianshiZhentiBaodian20212022Fix1/js/__init__.py
niu_keyun_yinggang_mianshi_zhenti_baodian_2021_2022_fix1-2025.3.25.0.dist-info/METADATA
niu_keyun_yinggang_mianshi_zhenti_baodian_2021_2022_fix1-2025.3.25.0.dist-info/WHEEL
niu_keyun_yinggang_mianshi_zhenti_baodian_2021_2022_fix1-2025.3.25.0.dist-info/entry_points.txt
niu_keyun_yinggang_mianshi_zhenti_baodian_2021_2022_fix1-2025.3.25.0.dist-info/top_level.txt
niu_keyun_yinggang_mianshi_zhenti_baodian_2021_2022_fix1-2025.3.25.0.dist-info/RECORD
